[{"title":"О списке","type":0,"sectionRef":"#","url":"/en/about/","content":"","keywords":""},{"title":"Лицензия​","type":1,"pageTitle":"О списке","url":"/en/about/#license","content":"Текстовая (документальная) часть доступна по лицензии CC BY-NC-SA 4.0. Кодовая часть доступна по лицензии GNU-GPLv3. "},{"title":"Армения","type":0,"sectionRef":"#","url":"/en/armenia/","content":"","keywords":"сайты чаты Армения"},{"title":"Сайты​","type":1,"pageTitle":"Армения","url":"/en/armenia/#sites","content":"Армения. Путеводитель по переезду.ВНЖ, банки, налоги в Армении "},{"title":"Чаты​","type":1,"pageTitle":"Армения","url":"/en/armenia/#chats","content":"Ковчег. Армения.Армения: ВНЖ, банки, налоги | ЧатIT В ЕРЕВАНЕ ЧАТCrypto Armenia Крипто Армения "},{"title":"Аргентина","type":0,"sectionRef":"#","url":"/en/argentina/","content":"","keywords":"сайты чаты Аргентина"},{"title":"Сайты​","type":1,"pageTitle":"Аргентина","url":"/en/argentina/#sites","content":"Иммиграция RuArgentina. FAQ "},{"title":"Чаты​","type":1,"pageTitle":"Аргентина","url":"/en/argentina/#chats","content":"Аргентина For You | by BlacksmithRuArgentina.ЧатРоды в Аргентине Chat | Giving Birth in Argentina "},{"title":"Шри-Ланка","type":0,"sectionRef":"#","url":"/en/sri-lanka/","content":"","keywords":"сайты чаты Шри-Ланка"},{"title":"Сайты​","type":1,"pageTitle":"Шри-Ланка","url":"/en/sri-lanka/#sites","content":"You open - Шри-ЛанкаСолнце Шри ЛанкиLanka.ruHikka.ru "},{"title":"Чаты​","type":1,"pageTitle":"Шри-Ланка","url":"/en/sri-lanka/#chats","content":"ОТЪЕХАВШИЕШри-Ланка (sun-lanka.ru)Шри-Ланка (Эмигранты 360)Шри-Ланка (lanka.ru)ВЕЛИГАМНОСТЬ danger Рекомендуется воздержаться от контактов с администрацией чата ВЕЛИГАМНОСТЬ, из-за агрессивного отношения к пользователям. "},{"title":"Турция","type":0,"sectionRef":"#","url":"/en/turkey/","content":"","keywords":"сайты чаты Турция"},{"title":"Сайты​","type":1,"pageTitle":"Турция","url":"/en/turkey/#sites","content":"Гайд по релокации в Стамбул от istanbulgogogoТурция. Гайд по переезду в 2022 году.Relocation.guide ТурцияТелеграмм канал Стамбульский канал. "},{"title":"Чаты​","type":1,"pageTitle":"Турция","url":"/en/turkey/#chats","content":"Ковчег | ТурцияПоехали в Стамбул | ЧАТ "},{"title":"Германия","type":0,"sectionRef":"#","url":"/en/germany/","content":"","keywords":"сайты чаты Германия"},{"title":"Сайты​","type":1,"pageTitle":"Германия","url":"/en/germany/#sites","content":"Жизнь в Германии "},{"title":"Чаты​","type":1,"pageTitle":"Германия","url":"/en/germany/#chats","content":""},{"title":"Telegram​","type":1,"pageTitle":"Германия","url":"/en/germany/#telegram","content":"Общий чат Германия Берлин​ 🍉 Berlin Берлін 🇺🇦Чат канала «Берлинские события» Мюнхен​ ОбщийАвто-чатДенежныйНастольные игры Остальные города​ ФранкфуртИнгольштадтГамбург "},{"title":"Skype​","type":1,"pageTitle":"Германия","url":"/en/germany/#skype","content":"БерлинскийЖенский чат "},{"title":"Slack​","type":1,"pageTitle":"Германия","url":"/en/germany/#slack","content":"berlinru.slack.com - slack людей из Берлина и остальной Германии, более 2200 пользователей, чтобы получить инвайт заполните форму здесьGermany RU - альтернативный slack людей живущих и работающих в Германии, необходима регистрация по номеру телефона и обязательны реальные имена "},{"title":"Источники информации​","type":1,"pageTitle":"Германия","url":"/en/germany/#источники-информации","content":"Жизнь в Германии "}]